{
  "user": {
    "username": "username_123",
    "avatarUrl": "../../src/images/icons/User_Profile_Image_NoLogo.png",
    "dateJoined": "2025-01-01",
    "favoriteGenres": ["Fantasy", "Mystery", "Science Fiction", "Romance", "Thriller"]
  },
  "book": {
    "coverUrl": "/src/assets/icons/BookCover.svg",
    "seriesTitle": "The Great Adventures Series",
    "title": "The Mysterious Island",
    "summary": "A thrilling adventure of castaways, hidden treasures, and unexpected encounters on a remote island.",
    "isbn": "978-1-23456-789-7",
    "genres": ["Adventure", "Mystery", "Classic"],
    "averageRating": 4.2,
    "reviews": [
      {
        "username": "BookLover123",
        "rating": 5,
        "text": "Absolutely loved the twists and turns!"
      },
      {
        "username": "IslandFan",
        "rating": 4,
        "text": "A fun read, though some parts felt slow."
      }
    ]
  },
  "userReview": {
    "avatarUrl": "../../src/images/icons/User_Profile_Image_NoLogo.png",
    "username": "MyUsername123"
  },
  "otherReviews": [
    {
      "id": 1,
      "username": "JaneDoe",
      "avatarUrl": "../../src/images/icons/User_Profile_Image_NoLogo.png",
      "rating": 4,
      "text": "Great read. Loved the characters!"
    },
    {
      "id": 2,
      "username": "JohnSmith",
      "avatarUrl": "../../src/images/icons/User_Profile_Image_NoLogo.png",
      "rating": 3,
      "text": "Enjoyable, but the pacing was off."
    }
  ],
  "similarBooks": [
    {
      "isbn": "978-1-00000-111-1",
      "coverUrl": "/src/assets/icons/BookCover.svg",
      "title": "Island of Secrets",
      "rating": 4,
      "averageRating": 4.1,
      "genres": ["Adventure", "Fantasy"],
      "isFavorite": false
    },
    {
      "isbn": "978-1-00000-222-2",
      "coverUrl": "/src/assets/icons/BookCover.svg",
      "title": "Treasure of the Lost World",
      "rating": 5,
      "averageRating": 4.7,
      "genres": ["Adventure", "Thriller"],
      "isFavorite": true
    },
    {
      "isbn": "978-1-00000-111-1",
      "coverUrl": "/src/assets/icons/BookCover.svg",
      "title": "Island of Secrets",
      "rating": 4,
      "averageRating": 4.1,
      "genres": ["Adventure", "Fantasy"],
      "isFavorite": false
    },
    {
      "isbn": "978-1-00000-222-2",
      "coverUrl": "/src/assets/icons/BookCover.svg",
      "title": "Treasure of the Lost World",
      "rating": 5,
      "averageRating": 4.7,
      "genres": ["Adventure", "Thriller"],
      "isFavorite": true
    },
    {
      "isbn": "978-1-00000-111-1",
      "coverUrl": "/src/assets/icons/BookCover.svg",
      "title": "Island of Secrets",
      "rating": 4,
      "averageRating": 4.1,
      "genres": ["Adventure", "Fantasy"],
      "isFavorite": false
    },
    {
      "isbn": "978-1-00000-222-2",
      "coverUrl": "/src/assets/icons/BookCover.svg",
      "title": "Treasure of the Lost World",
      "rating": 5,
      "averageRating": 4.7,
      "genres": ["Adventure", "Thriller"],
      "isFavorite": true
    }
  ,
    {
      "isbn": "978-1-00000-111-1",
      "coverUrl": "/src/assets/icons/BookCover.svg",
      "title": "Island of Secrets",
      "rating": 4,
      "averageRating": 4.1,
      "genres": ["Adventure", "Fantasy"],
      "isFavorite": false
    },
    {
      "isbn": "978-1-00000-222-2",
      "coverUrl": "/src/assets/icons/BookCover.svg",
      "title": "Treasure of the Lost World",
      "rating": 5,
      "averageRating": 4.7,
      "genres": ["Adventure", "Thriller"],
      "isFavorite": true
    }
  ,
    {
      "isbn": "978-1-00000-111-1",
      "coverUrl": "/src/assets/icons/BookCover.svg",
      "title": "Island of Secrets",
      "rating": 4,
      "averageRating": 4.1,
      "genres": ["Adventure", "Fantasy"],
      "isFavorite": false
    },
    {
      "isbn": "978-1-00000-222-2",
      "coverUrl": "/src/assets/icons/BookCover.svg",
      "title": "Treasure of the Lost World",
      "rating": 5,
      "averageRating": 4.7,
      "genres": ["Adventure", "Thriller"],
      "isFavorite": true
    },
    {
      "isbn": "978-1-00000-111-1",
      "coverUrl": "/src/assets/icons/BookCover.svg",
      "title": "Island of Secrets",
      "rating": 4,
      "averageRating": 4.1,
      "genres": ["Adventure", "Fantasy"],
      "isFavorite": false
    },
    {
      "isbn": "978-1-00000-222-2",
      "coverUrl": "/src/assets/icons/BookCover.svg",
      "title": "Treasure of the Lost World",
      "rating": 5,
      "averageRating": 4.7,
      "genres": ["Adventure", "Thriller"],
      "isFavorite": true
    }
  ]
}
